Workbook

Sheet 總覽
B2: 安幸有限公司 | J2: An Xing Co.
B3: 老闆版損益 ・ 一一五年八月 ・ 新台幣元 ・ 內部文件
B6: 實際營收 | D6: 實際成本 | F6: 實際損益 | H6: 利潤率 | J6: Jim 實拿
B7: Revenue | D7: Cost | F7: Net | H7: Margin | J7: Owner's share
B8: =老闆總表!D14 -> 9733398.2 | D8: =老闆總表!J14 -> 8149017 | F8: =老闆總表!K14 -> 1584381.2 | H8: =老闆總表!L14 -> 0.16277781 | J8: =Jim個人!D14 -> 865617.26
B11: 各案子實際損益 | D11: Actual net by property
B30: 各案子利潤率 | D30: Margin by property
B47: 讀法
B48: 正隆貢獻 80.2% 營收、80.6% 損益;正隆一案佔 Jim 實拿 73.8%。
B49: 三個負數——辦公室 −125,603:薪資獎金 441,374+自身營運費 148,939,內部收入 464,710(正隆 200,000・時兆 90,000・開封 48,000・JPR 40,000+各案清潔費 87,510−調整 800)未足額覆蓋,屬結構性;JPR −17,508;復興 −8,533(零營收)。
B50: 改「報表數據」與「調整明細」的藍字,全表與圖自動重算。

Sheet 老闆總表
A1: 各案子實際損益 | M1: Actual P&L by Property
A2: 一一五年八月 ・ 新台幣元 ・ 藍字可改,其餘公式連動
A4: 案子 | B4: 報表營業收入 | C4: 營收調整 | D4: 實際營業收入 | E4: 報表營運費用 | F4: 成本調整 | G4: 付房東租金 | H4: 付安幸辦公室 | I4: 薪資獎金 | J4: 實際總成本 | K4: 實際損益 | L4: 利潤率 | M4: 本月調整說明
A5: 正隆 | B5: =SUMIFS(報表數據!B:B,報表數據!A:A,A5) -> 7803072 | C5: =SUMIFS(調整明細!D:D,調整明細!A:A,A5,調整明細!B:B,"營收調整") -> 0 | D5: =B5+C5 -> 7803072 | E5: =SUMIFS(報表數據!C:C,報表數據!A:A,A5) -> 6526236 | F5: =SUMIFS(調整明細!D:D,調整明細!A:A,A5,調整明細!B:B,"成本調整") -> -200000 | G5: =SUMIFS(調整明細!D:D,調整明細!A:A,A5,調整明細!B:B,"房東租金") -> 0 | H5: =SUMIFS(調整明細!D:D,調整明細!A:A,A5,調整明細!B:B,"付安幸辦公室") -> 200000 | I5: =SUMIFS(調整明細!D:D,調整明細!A:A,A5,調整明細!B:B,"薪資") -> 0 | J5: =E5+F5+G5+H5+I5 -> 6526236 | K5: =D5-J5 -> 1276836 | L5: =IF(D5=0,"",K5/D5) -> 0.16363248 | M5: 無調整
A6: 時兆 | B6: =SUMIFS(報表數據!B:B,報表數據!A:A,A6) -> 815616 | C6: =SUMIFS(調整明細!D:D,調整明細!A:A,A6,調整明細!B:B,"營收調整") -> 0 | D6: =B6+C6 -> 815616 | E6: =SUMIFS(報表數據!C:C,報表數據!A:A,A6) -> 455194 | F6: =SUMIFS(調整明細!D:D,調整明細!A:A,A6,調整明細!B:B,"成本調整") -> 0 | G6: =SUMIFS(調整明細!D:D,調整明細!A:A,A6,調整明細!B:B,"房東租金") -> 0 | H6: =SUMIFS(調整明細!D:D,調整明細!A:A,A6,調整明細!B:B,"付安幸辦公室") -> 90000 | I6: =SUMIFS(調整明細!D:D,調整明細!A:A,A6,調整明細!B:B,"薪資") -> 0 | J6: =E6+F6+G6+H6+I6 -> 545194 | K6: =D6-J6 -> 270422 | L6: =IF(D6=0,"",K6/D6) -> 0.33155554 | M6: 加 每月付安幸辦公室薪資 90,000
A7: 開封 | B7: =SUMIFS(報表數據!B:B,報表數據!A:A,A7) -> 282930 | C7: =SUMIFS(調整明細!D:D,調整明細!A:A,A7,調整明細!B:B,"營收調整") -> 0 | D7: =B7+C7 -> 282930 | E7: =SUMIFS(報表數據!C:C,報表數據!A:A,A7) -> 174391 | F7: =SUMIFS(調整明細!D:D,調整明細!A:A,A7,調整明細!B:B,"成本調整") -> 0 | G7: =SUMIFS(調整明細!D:D,調整明細!A:A,A7,調整明細!B:B,"房東租金") -> 0 | H7: =SUMIFS(調整明細!D:D,調整明細!A:A,A7,調整明細!B:B,"付安幸辦公室") -> 48000 | I7: =SUMIFS(調整明細!D:D,調整明細!A:A,A7,調整明細!B:B,"薪資") -> 0 | J7: =E7+F7+G7+H7+I7 -> 222391 | K7: =D7-J7 -> 60539 | L7: =IF(D7=0,"",K7/D7) -> 0.21397165 | M7: 加 每月付安幸辦公室人事費 48,000
A8: 南京 | B8: =SUMIFS(報表數據!B:B,報表數據!A:A,A8) -> 214216 | C8: =SUMIFS(調整明細!D:D,調整明細!A:A,A8,調整明細!B:B,"營收調整") -> 0 | D8: =B8+C8 -> 214216 | E8: =SUMIFS(報表數據!C:C,報表數據!A:A,A8) -> 92961 | F8: =SUMIFS(調整明細!D:D,調整明細!A:A,A8,調整明細!B:B,"成本調整") -> 0 | G8: =SUMIFS(調整明細!D:D,調整明細!A:A,A8,調整明細!B:B,"房東租金") -> 25000 | H8: =SUMIFS(調整明細!D:D,調整明細!A:A,A8,調整明細!B:B,"付安幸辦公室") -> 0 | I8: =SUMIFS(調整明細!D:D,調整明細!A:A,A8,調整明細!B:B,"薪資") -> 0 | J8: =E8+F8+G8+H8+I8 -> 117961 | K8: =D8-J8 -> 96255 | L8: =IF(D8=0,"",K8/D8) -> 0.44933618 | M8: 加 南京5 房東租金 25,000
A9: JPR | B9: =SUMIFS(報表數據!B:B,報表數據!A:A,A9) -> 81777 | C9: =SUMIFS(調整明細!D:D,調整明細!A:A,A9,調整明細!B:B,"營收調整") -> 0 | D9: =B9+C9 -> 81777 | E9: =SUMIFS(報表數據!C:C,報表數據!A:A,A9) -> 17285 | F9: =SUMIFS(調整明細!D:D,調整明細!A:A,A9,調整明細!B:B,"成本調整") -> 0 | G9: =SUMIFS(調整明細!D:D,調整明細!A:A,A9,調整明細!B:B,"房東租金") -> 42000 | H9: =SUMIFS(調整明細!D:D,調整明細!A:A,A9,調整明細!B:B,"付安幸辦公室") -> 40000 | I9: =SUMIFS(調整明細!D:D,調整明細!A:A,A9,調整明細!B:B,"薪資") -> 0 | J9: =E9+F9+G9+H9+I9 -> 99285 | K9: =D9-J9 -> -17508 | L9: =IF(D9=0,"",K9/D9) -> -0.21409443 | M9: 加 房東租金 42,000 + 每月付安幸辦公室 40,000
A10: 台視 | B10: =SUMIFS(報表數據!B:B,報表數據!A:A,A10) -> 68554 | C10: =SUMIFS(調整明細!D:D,調整明細!A:A,A10,調整明細!B:B,"營收調整") -> 0 | D10: =B10+C10 -> 68554 | E10: =SUMIFS(報表數據!C:C,報表數據!A:A,A10) -> 9104 | F10: =SUMIFS(調整明細!D:D,調整明細!A:A,A10,調整明細!B:B,"成本調整") -> 0 | G10: =SUMIFS(調整明細!D:D,調整明細!A:A,A10,調整明細!B:B,"房東租金") -> 30000 | H10: =SUMIFS(調整明細!D:D,調整明細!A:A,A10,調整明細!B:B,"付安幸辦公室") -> 0 | I10: =SUMIFS(調整明細!D:D,調整明細!A:A,A10,調整明細!B:B,"薪資") -> 0 | J10: =E10+F10+G10+H10+I10 -> 39104 | K10: =D10-J10 -> 29450 | L10: =IF(D10=0,"",K10/D10) -> 0.42958835 | M10: 加 房東租金 30,000
A11: 亞曼尼 | B11: =SUMIFS(報表數據!B:B,報表數據!A:A,A11) -> 5744 | C11: =SUMIFS(調整明細!D:D,調整明細!A:A,A11,調整明細!B:B,"營收調整") -> -3220.8 | D11: =B11+C11 -> 2523.2 | E11: =SUMIFS(報表數據!C:C,報表數據!A:A,A11) -> 2820.28 | F11: =SUMIFS(調整明細!D:D,調整明細!A:A,A11,調整明細!B:B,"成本調整") -> -2820.28 | G11: =SUMIFS(調整明細!D:D,調整明細!A:A,A11,調整明細!B:B,"房東租金") -> 0 | H11: =SUMIFS(調整明細!D:D,調整明細!A:A,A11,調整明細!B:B,"付安幸辦公室") -> 0 | I11: =SUMIFS(調整明細!D:D,調整明細!A:A,A11,調整明細!B:B,"薪資") -> 0 | J11: =E11+F11+G11+H11+I11 -> 0 | K11: =D11-J11 -> 2523.2 | L11: =IF(D11=0,"",K11/D11) -> 1 | M11: Jim 只收營業額 30%(1,723)+清潔費 800;報表費用 2,820 不歸 Jim
A12: 復興 | B12: =SUMIFS(報表數據!B:B,報表數據!A:A,A12) -> 0 | C12: =SUMIFS(調整明細!D:D,調整明細!A:A,A12,調整明細!B:B,"營收調整") -> 0 | D12: =B12+C12 -> 0 | E12: =SUMIFS(報表數據!C:C,報表數據!A:A,A12) -> 8533 | F12: =SUMIFS(調整明細!D:D,調整明細!A:A,A12,調整明細!B:B,"成本調整") -> 0 | G12: =SUMIFS(調整明細!D:D,調整明細!A:A,A12,調整明細!B:B,"房東租金") -> 0 | H12: =SUMIFS(調整明細!D:D,調整明細!A:A,A12,調整明細!B:B,"付安幸辦公室") -> 0 | I12: =SUMIFS(調整明細!D:D,調整明細!A:A,A12,調整明細!B:B,"薪資") -> 0 | J12: =E12+F12+G12+H12+I12 -> 8533 | K12: =D12-J12 -> -8533 | L12: =IF(D12=0,"",K12/D12) | M12: 無調整(本月無營收)
A13: 安幸辦公室 | B13: =SUMIFS(報表數據!B:B,報表數據!A:A,A13) -> 287510 | C13: =SUMIFS(調整明細!D:D,調整明細!A:A,A13,調整明細!B:B,"營收調整") -> 177200 | D13: =B13+C13 -> 464710 | E13: =SUMIFS(報表數據!C:C,報表數據!A:A,A13) -> 148939 | F13: =SUMIFS(調整明細!D:D,調整明細!A:A,A13,調整明細!B:B,"成本調整") -> 0 | G13: =SUMIFS(調整明細!D:D,調整明細!A:A,A13,調整明細!B:B,"房東租金") -> 0 | H13: =SUMIFS(調整明細!D:D,調整明細!A:A,A13,調整明細!B:B,"付安幸辦公室") -> 0 | I13: =SUMIFS(調整明細!D:D,調整明細!A:A,A13,調整明細!B:B,"薪資") -> 441374 | J13: =E13+F13+G13+H13+I13 -> 590313 | K13: =D13-J13 -> -125603 | L13: =IF(D13=0,"",K13/D13) -> -0.27028254 | M13: 加 內部收入 178,000;亞曼尼清潔費移列;加薪資獎金 441,374
A14: 合計 | B14: =SUM(B5:B13) -> 9559419 | C14: =SUM(C5:C13) -> 173979.2 | D14: =SUM(D5:D13) -> 9733398.2 | E14: =SUM(E5:E13) -> 7435463.3 | F14: =SUM(F5:F13) -> -202820.28 | G14: =SUM(G5:G13) -> 97000 | H14: =SUM(H5:H13) -> 378000 | I14: =SUM(I5:I13) -> 441374 | ... K14: =SUM(K5:K13) -> 1584381.2 | L14: =IF(D14=0,"",K14/D14) -> 0.16277781 | M14: 內部往來在合計中自動抵銷

Sheet Jim個人
A1: Jim 個人實拿 | F1: Owner's Share
A2: 依持股比例 ・ 持股(藍字)可改
A4: 案子 | B4: 實際損益 | C4: Jim 持股 | D4: Jim 實拿 | E4: 其他股東 | F4: 備註
A5: 正隆 | B5: =老闆總表!K5 -> 1276836 | C5: 0.5 | D5: =B5*C5 -> 638418 | E5: =B5-D5 -> 638418 | F5: 50%
A6: 時兆 | B6: =老闆總表!K6 -> 270422 | C6: 1 | D6: =B6*C6 -> 270422 | E6: =B6-D6 -> 0 | F6: 100%
A7: 開封 | B7: =老闆總表!K7 -> 60539 | C7: 0.54 | D7: =B7*C7 -> 32691.06 | E7: =B7-D7 -> 27847.94 | F7: 54%
A8: 南京 | B8: =老闆總表!K8 -> 96255 | C8: 0.33333333 | D8: =B8*C8 -> 32085 | E8: =B8-D8 -> 64170 | F8: 1/3(與 JPR 合併算)
A9: JPR | B9: =老闆總表!K9 -> -17508 | C9: 0.33333333 | D9: =B9*C9 -> -5836 | E9: =B9-D9 -> -11672 | F9: 1/3(與南京合併算)
A10: 台視 | B10: =老闆總表!K10 -> 29450 | C10: 1 | D10: =B10*C10 -> 29450 | E10: =B10-D10 -> 0 | F10: 100%
A11: 亞曼尼 | B11: =老闆總表!K11 -> 2523.2 | C11: 1 | D11: =B11*C11 -> 2523.2 | E11: =B11-D11 -> 0 | F11: 100%;營業額 30%+清潔費,無成本
A12: 復興 | B12: =老闆總表!K12 -> -8533 | C12: 1 | D12: =B12*C12 -> -8533 | E12: =B12-D12 -> 0 | F12: 100%
A13: 安幸辦公室 | B13: =老闆總表!K13 -> -125603 | C13: 1 | D13: =B13*C13 -> -125603 | E13: =B13-D13 -> 0 | F13: 100%;含內部收入
A14: 合計 | B14: =SUM(B5:B13) -> 1584381.2 | C14: =IF(B14=0,"",D14/B14) -> 0.54634406 | D14: =SUM(D5:D13) -> 865617.26 | E14: =SUM(E5:E13) -> 718763.94 | F14: 持股欄=實拿÷全案損益

Sheet 報表數據
A1: 報表原始數據 | E1: Source Figures
A2: 藍字=自公司報表手填,改這裡全表重算
A4: 案子 | B4: 報表營業收入 | C4: 報表營運費用 | D4: 報表營運損益 | E4: 來源 / 備註
A5: 正隆 | B5: 7803072 | C5: 6526236 | D5: =B5-C5 -> 1276836 | E5: 正隆_收支報表_115年8月_FINAL_v4;保證金 200,000 屬融資往來不計入
A6: 時兆 | B6: 815616 | C6: 455194 | D6: =B6-C6 -> 360422 | E6: 各物業_收支報表_115年8月_v4「收支總覽」
A7: 開封 | B7: 282930 | C7: 174391 | D7: =B7-C7 -> 108539 | E7: 各物業_收支報表_115年8月_v4「收支總覽」
A8: 南京 | B8: 214216 | C8: 92961 | D8: =B8-C8 -> 121255 | E8: 各物業_收支報表;其中南京5營收 99,000
A9: JPR | B9: 81777 | C9: 17285 | D9: =B9-C9 -> 64492 | E9: 各物業_收支報表「收支總覽」
A10: 台視 | B10: 68554 | C10: 9104 | D10: =B10-C10 -> 59450 | E10: 各物業_收支報表「收支總覽」
A11: 亞曼尼 | B11: 5744 | C11: 2820.28 | D11: =B11-C11 -> 2923.72 | E11: 各物業_收支報表;5,744 為亞曼尼總營業額
A12: 復興 | B12: 0 | C12: 8533 | D12: =B12-C12 -> -8533 | E12: 各物業_收支報表;本月無營收
A13: 安幸辦公室 | B13: 287510 | C13: 148939 | D13: =B13-C13 -> 138571 | E13: 營收皆為向各案收取之清潔/人事費(內部往來):87,510+正隆房務 200,000
A14: 合計 | B14: =SUM(B5:B13) -> 9559419 | C14: =SUM(C5:C13) -> 7435463.3 | D14: =SUM(D5:D13) -> 2123955.7

Sheet 調整明細
A1: 老闆版調整項目 | E1: Owner Adjustments
A2: 公司報表未列 ・ 藍字可改
A4: 案子 | B4: 調整類型 | C4: 項目 | D4: 金額 | E4: 計算方式 / 備註
A5: JPR | B5: 房東租金 | C5: JPR 月租(付房東) | D5: 42000 | E5: 固定月租
A6: 南京 | B6: 房東租金 | C6: 南京5 月租(付房東) | D6: 25000 | E6: 固定月租;南京5 本月營收 99,000
A7: 台視 | B7: 房東租金 | C7: 台視 月租(付房東) | D7: 30000 | E7: 固定月租
A8: JPR | B8: 付安幸辦公室 | C8: JPR 每月付安幸辦公室管理費 | D8: 40000 | E8: 固定每月;對應辦公室內部收入
A9: 開封 | B9: 付安幸辦公室 | C9: 開封 每月付安幸辦公室人事費 | D9: 48000 | E9: 公司報表已刪除之 48,000 於此加回
A10: 時兆 | B10: 付安幸辦公室 | C10: 時兆 每月付安幸辦公室薪資 | D10: 90000 | E10: 固定每月;對應辦公室內部收入
A11: 安幸辦公室 | B11: 營收調整 | C11: 內部收入:JPR 管理費 | D11: 40000 | E11: 對應:JPR 付安幸辦公室
A12: 安幸辦公室 | B12: 營收調整 | C12: 內部收入:開封 人事費 | D12: 48000 | E12: 對應:開封 付安幸辦公室
A13: 安幸辦公室 | B13: 營收調整 | C13: 內部收入:時兆 薪資 | D13: 90000 | E13: 對應:時兆 付安幸辦公室
A14: 亞曼尼 | B14: 營收調整 | C14: 營業額 70% 歸屋主(安幸抽 30%) | D14: -4020.8 | E14: 管理費=5,744×30%=1,723;70% 以負數調整
A15: 亞曼尼 | B15: 營收調整 | C15: 清潔費收入(房東付給 Jim) | D15: 800 | E15: 8/17 房務清潔;自辦公室移列至此
A16: 安幸辦公室 | B16: 營收調整 | C16: 亞曼尼清潔費移列 | D16: -800 | E16: 避免重複計算
... A21: 正隆 | B21: 付安幸辦公室 | C21: 正隆 房務人事費(付安幸辦公室) | D21: 200000 | E21: 對應安幸辦公室報表營收 287,510 內之 200,000——先前已入帳,現拉至檯面
A22: 安幸辦公室 | B22: 備註 | C22: 內部收入:正隆 200,000 已含在報表營收 287,510 內 | E22: 故不重複加回;辦公室內部收入合計 = 378,000(四案固定)+ 清潔費 87,510

Sheet 薪資明細
A1: 薪資與獎金明細 | D1: Payroll — Confidential
A2: 僅供老闆檢視 ・ 勿外流
A4: 類別 | B4: 撥款日 | C4: 員工 | D4: 金額
A5: 薪資 | B5: 09-11 | C5: 簡靜惠 | D5: 63055
A6: 薪資 | B6: 09-11 | C6: 謝邵瑛 | D6: 42375
A7: 薪資 | B7: 09-11 | C7: 張瓊月 | D7: 30762
A8: 薪資 | B8: 09-11 | C8: 羅大偉 | D8: 62191
A9: 薪資 | B9: 09-11 | C9: 王芊茹 | D9: 48453
A10: 薪資 | B10: 09-11 | C10: 張家綺 | D10: 40440
A11: 薪資 | B11: 09-11 | C11: 周庭玉 | D11: 40375
A12: 薪資 | B12: 09-11 | C12: 唐筑萱 | D12: 40515
A13: 薪資 | B13: 09-11 | C13: 游佳穎 | D13: 53708
A14: 薪資小計 | D14: =SUM(D5:D13) -> 421874
A15: 獎金 | B15: 09-16 | C15: 張家綺 | D15: 4000
A16: 獎金 | B16: 09-16 | C16: 謝邵瑛 | D16: 2000
A17: 獎金 | B17: 09-16 | C17: 周庭玉 | D17: 6500
A18: 獎金 | B18: 09-16 | C18: 張瓊月 | D18: 7000
A19: 獎金小計 | D19: =SUM(D15:D18) -> 19500
A20: 合計 | D20: =D14+D19 -> 441374

Sheet 說明
A1: 參數與說明 | B1: Notes
A2: 讀完再改數字
A5: 1 | B5: 本表為老闆內部版:在公司報表基礎上加入未列的三類——付房東租金、8 月薪資獎金、亞曼尼營收調整。
A6: 2 | B6: 公司報表數字放「報表數據」、調整放「調整明細」(皆藍字);「老闆總表」以 SUMIFS 連動,改藍字自動重算;「總覽」的數字與圖表全數連動總表。
A7: 3 | B7: 薪資獎金 441,374 全列「安幸辦公室」;各案每月固定付辦公室:JPR 40,000、開封 48,000、時兆 90,000——該案成本、辦公室內部收入,合計自動抵銷。
A8: 4 | B8: 正隆報表「薪資勞務」366,600 = 6B2 仲介費 165,000 + 付安幸辦公室房務人事費 200,000 + 魏伊漪 1,600。該 200,000 已於「調整明細」重分類至「付安幸辦公室」欄(成本調整 −200,000 對沖),正隆總成本不變;對應收入原本就在辦公室報表營收 287,510 內,未重複計算。
A9: 5 | B9: 辦公室營收 287,510 全為內部往來——單看該案時,它的收入不是外部收入。
A10: 6 | B10: 亞曼尼:Jim 只收營業額 30%(1,723)與清潔費 800;報表費用 2,820 不歸 Jim;清潔費自辦公室移列亞曼尼,合計不變。
A11: 7 | B11: 正隆裝潢保證金 200,000 屬押金(融資往來),不計入營運損益。
A12: 8 | B12: 8/5 獎金 90,000 已自公司報表刪除;本表以薪轉戶/獎金檔實際撥款為準。
A13: 9 | B13: Jim 持股:正隆 50%、開封 54%、JPR 與南京各 1/3,其餘 100%(「Jim個人」藍字可改)。
A14: 10 | B14: 安幸辦公室內部收入全貌:四案固定 378,000(正隆 200,000/時兆 90,000/開封 48,000/JPR 40,000)+各案清潔費 87,510;對比薪資 441,374 與自身營運費 148,939,月缺口 125,603 為老闆自留之管理成本。
